<?xml version="1.0" encoding="utf-8" ?>
<dwsync>
<file name="aspectos-adicionales.blade.php" server="ftp.eesppukllasunchis.edu.pe" local="133528457660000000" remote="133730019600000000" Dst="0" />
<file name="aspectos-educativos.blade.php" server="ftp.eesppukllasunchis.edu.pe" local="133542498484943791" remote="133730019600000000" Dst="0" />
<file name="aspectos-socioeconomico.blade.php" server="ftp.eesppukllasunchis.edu.pe" local="133585383671061137" remote="133730723400000000" Dst="0" />
<file name="aspectos-vivienda.blade.php" server="ftp.eesppukllasunchis.edu.pe" local="133585384873290683" remote="133730723400000000" Dst="0" />
<file name="caracteristicas-familiares.blade.php" server="ftp.eesppukllasunchis.edu.pe" local="133585382214021592" remote="133730723400000000" Dst="0" />
<file name="create.blade.php" server="ftp.eesppukllasunchis.edu.pe" local="133571681776211319" remote="133730723400000000" Dst="0" />
<file name="datos-personales.blade.php" server="ftp.eesppukllasunchis.edu.pe" local="133585351796286217" remote="133730723400000000" Dst="0" />
<file name="edit.blade.php" server="ftp.eesppukllasunchis.edu.pe" local="133685616462053461" remote="133730723400000000" Dst="0" />
<file name="index.blade.php" server="ftp.eesppukllasunchis.edu.pe" local="133735878992420811" remote="133747897200000000" Dst="0" />
<file name="show.blade.php" server="ftp.eesppukllasunchis.edu.pe" local="133679728306176970" remote="133730723400000000" Dst="0" />
<file name="aspectos-salud-culturales.blade.php" server="ftp.eesppukllasunchis.edu.pe" local="133609755341337184" remote="133730723400000000" Dst="0" />
<file name="filtro.blade.php" server="ftp.eesppukllasunchis.edu.pe" local="133679688451124104" remote="133730723400000000" Dst="0" />
<file name="ficha.blade.php" server="ftp.eesppukllasunchis.edu.pe" local="133680592919946132" remote="133730723400000000" Dst="0" />
</dwsync>