<?xml version="1.0" encoding="utf-8" ?>
<dwsync>
<file name="EnlacesController.php" server="ftp.eesppukllasunchis.edu.pe" local="133614916707995244" remote="133677285600000000" Dst="0" />
<file name="Controller.php" server="ftp.eesppukllasunchis.edu.pe" local="133524075180000000" remote="133677285600000000" Dst="0" />
<file name="AlumnoController.php" server="ftp.eesppukllasunchis.edu.pe" local="133679687863834855" remote="133679889000000000" Dst="0" />
<file name="AdminController.php" server="ftp.eesppukllasunchis.edu.pe" local="133614047140266956" remote="133677285600000000" Dst="0" />
<file name="CicloController.php" server="ftp.eesppukllasunchis.edu.pe" local="133682933855024721" remote="133683123000000000" Dst="0" />
<file name="CursoController.php" server="ftp.eesppukllasunchis.edu.pe" local="133583685235029398" remote="133677285600000000" Dst="0" />
<file name="HomeController.php" server="ftp.eesppukllasunchis.edu.pe" local="133584661932146387" remote="133677285600000000" Dst="0" />
<file name="ProgramaController.php" server="ftp.eesppukllasunchis.edu.pe" local="133589654261414924" remote="133677285600000000" Dst="0" />
<file name="vistasAlumnosController.php" server="ftp.eesppukllasunchis.edu.pe" local="133535309460000000" remote="133677285600000000" Dst="0" />
<file name="BolsaController.php" server="ftp.eesppukllasunchis.edu.pe" local="133619913337799158" remote="133620096000000000" Dst="0" />
<file name="PostulanteController.php" server="ftp.eesppukllasunchis.edu.pe" local="133613182566986372" remote="133677285600000000" Dst="0" />
</dwsync>